yyinput/__init__.py
yyinput/config/__init__.py
yyinput/config/config.py
yyinput/dbasr/.rdm.md
yyinput/dbasr/__init__.py
yyinput/dbasr/dbasr.py
yyinput/dbasr/dbasr_tests/test.py
yyinput/dbasr/sauc.py
yyinput/dbasr/temp_recording.wav
yyinput/main/__init__.py
yyinput/main/main.py
yyinput/recorder/__init__.py
yyinput/recorder/recorder.py
yyinput-1.1.11.dist-info/WHEEL
yyinput-1.1.11.dist-info/entry_points.txt
yyinput-1.1.11.dist-info/METADATA
yyinput-1.1.11.dist-info/RECORD
