Metadata-Version: 2.3
Name: yyinput
Version: 1.1.11
Summary: 语音模型测试工具
Author: lipanpan-hub
Author-email: lipanpan-hub <47287977+lipanpan-hub@users.noreply.github.com>
Requires-Dist: aiohttp>=3.12.15
Requires-Dist: fire>=0.7.1
Requires-Dist: keyboard>=0.13.5
Requires-Dist: prompt-toolkit>=3.0.52
Requires-Dist: psutil>=7.0.0
Requires-Dist: pyaudio>=0.2.14
Requires-Dist: pyautogui>=0.9.54
Requires-Dist: pygetwindow>=0.0.9
Requires-Dist: pyperclip>=1.9.0
Requires-Dist: requests>=2.32.5
Requires-Python: >=3.13
